{
    "type":"FeatureCollection",
    "crs": {
        "type": "name",
          "properties": {
            "name": "EPSG:4326"
          }
    },
    "features":[
        {
            "type":"Feature",
            "properties":{
                "name": "Chesterfield Inlet"

            },
            "geometry":{
                "coordinates":[-90.7398823499868,63.3481836986259],
                "type":"Point"
            }
        }
    ]
}